RaphaelSomaDIT/__init__.py
RaphaelSomaDIT-2.6.dist-info/LICENSE
RaphaelSomaDIT-2.6.dist-info/LICENSE.txt
RaphaelSomaDIT-2.6.dist-info/METADATA
RaphaelSomaDIT-2.6.dist-info/WHEEL
RaphaelSomaDIT-2.6.dist-info/top_level.txt
RaphaelSomaDIT-2.6.dist-info/RECORD
