Metadata-Version: 2.1
Name: RaphaelSomaDIT
Version: 2.6
Summary: A SOMA API for obtaining student information of DIT
Home-page: https://github.com/raphael08/RaphaelSOMADIT.git
Author: Raphael Sifael Mkilya
Author-email: rsiphael@gmail.com
Classifier: Programming Language :: Python :: 3
Classifier: License :: OSI Approved :: MIT License
Classifier: Operating System :: OS Independent
License-File: LICENSE
License-File: LICENSE.txt
